{
    "name":"Canada",
    "children": [
        {
            "name":"Ontario",
            "population":13448494,
            "children":[
                {
                    "name":"Toronto",
                    "population":2731571
                }
            ]
        },
        {
            "name":"Quebec",
            "population":8164361,
            "children":[
                {
                    "name":"Montreal",
                    "population":1704694
                }
            ]
        },
        {
            "name":"British Columbia",
            "population":4648055,
            "children":[
                {
                    "name":"Vancouver",
                    "population":2463431
                }
            ]
        },
        {
            "name":"Alberta",
            "population":4067175,
            "children":[
                {
                    "name":"Calgary",
                    "population":1392609
                }
            ]
        },
        {
            "name":"Manitoba",
            "population":1278365,
            "children":[
                {
                    "name":"Winnepeg",
                    "population":778500
                }
            ]
        },
        {
            "name":"Saskatchewan",
            "population":1098352,
            "children":[
                {
                    "name":"Saskatoon",
                    "population":246376
                }
            ]
        },
        {
            "name":"Nova Scotia",
            "population":971395,
            "children":[
                {
                    "name":"Halifax",
                    "population":403131
                }
            ]
        },
        {
            "name":"New Brunswick",
            "population":747101,
            "children":[
                {
                    "name":"Moncton",
                    "population":71889
                }
            ]
        },
        {
            "name":"Newfoundland and Labrador",
            "population":519716,
            "children":[
                {
                    "name":"St. John's",
                    "population":219207
                }
            ]
        },
        {
            "name":"Prince Edward Island",
            "population":142907,
            "children":[
                {
                    "name":"Charlettetown",
                    "population":36094
                }
            ]
        },
        {
            "name":"Northwest Territories",
            "population":41786,
            "children":[
                {
                    "name":"Yellowknife",
                    "population":19569
                }
            ]
        },
        {
            "name":"Nunavut",
            "population":35944,
            "children":[
                {
                    "name":"Iqaluit",
                    "population":7740
                }
            ]
        },
        {
            "name":"Yukon",
            "population":35874,
            "children":[
                {
                    "name":"Whitehorse",
                    "population":25085
                }
            ]
        }
    ]
}